gommit/__init__.py
gommit/gommit.py
gommit-0.3.1.dist-info/licenses/LICENSE
gommit-0.3.1.dist-info/METADATA
gommit-0.3.1.dist-info/WHEEL
gommit-0.3.1.dist-info/entry_points.txt
gommit-0.3.1.dist-info/top_level.txt
gommit-0.3.1.dist-info/RECORD
