Metadata-Version: 2.4
Name: gommit
Version: 0.3.1
Summary: Generate Git commit messages using an OpenAI-compatible API
Home-page: https://github.com/MostafaMotahari/gommit
Author: Mostafa Motahari
Author-email: mostafamotahari2004@gmail.com
Classifier: Programming Language :: Python :: 3
Classifier: License :: OSI Approved :: MIT License
Classifier: Operating System :: OS Independent
Requires-Python: >=3.6
License-File: LICENSE
Requires-Dist: openai>=1.0.0
Requires-Dist: colorama>=0.4.6
Dynamic: author
Dynamic: author-email
Dynamic: classifier
Dynamic: description
Dynamic: description-content-type
Dynamic: home-page
Dynamic: license-file
Dynamic: requires-dist
Dynamic: requires-python
Dynamic: summary
